veryfi/__init__.py
veryfi/a_docs.py
veryfi/bank_statements.py
veryfi/bussines_cards.py
veryfi/checks.py
veryfi/client.py
veryfi/client_base.py
veryfi/documents.py
veryfi/errors.py
veryfi/w2s.py
veryfi/w8s.py
veryfi/w9s.py
veryfi/_documents/__init__.py
veryfi/_documents/line_items.py
veryfi/_documents/pdf_split.py
veryfi/_documents/tags.py
veryfi/_w2s/__init__.py
veryfi/_w2s/w2_split.py
veryfi-5.0.0.dist-info/licenses/LICENSE
veryfi-5.0.0.dist-info/METADATA
veryfi-5.0.0.dist-info/WHEEL
veryfi-5.0.0.dist-info/entry_points.txt
veryfi-5.0.0.dist-info/pbr.json
veryfi-5.0.0.dist-info/top_level.txt
veryfi-5.0.0.dist-info/RECORD
