Metadata-Version: 2.4
Name: veryfi
Version: 5.0.0
Home-page: https://github.com/veryfi/veryfi-python
Author: Veryfi, Inc.
Author-email: support@veryfi.com
License: MIT
Keywords: veryfi, veryfi.com, ocr api
Classifier: Development Status :: 5 - Production/Stable
Classifier: Programming Language :: Python :: 3.9
Classifier: Programming Language :: Python :: 3.10
Classifier: Programming Language :: Python :: 3.11
Classifier: Programming Language :: Python :: 3.12
Classifier: Programming Language :: Python :: Implementation :: CPython
License-File: LICENSE
Requires-Dist: requests>=2.22.0
Dynamic: author
Dynamic: author-email
Dynamic: description
Dynamic: keywords
Dynamic: license
Dynamic: license-file
Dynamic: requires-dist
